KaiyuanRuanjianZhinanFix1/README.md
KaiyuanRuanjianZhinanFix1/__init__.py
KaiyuanRuanjianZhinanFix1/__main__.py
KaiyuanRuanjianZhinanFix1/file.epub
KaiyuanRuanjianZhinanFix1/index.html
KaiyuanRuanjianZhinanFix1/css/__init__.py
KaiyuanRuanjianZhinanFix1/css/annotations.css
KaiyuanRuanjianZhinanFix1/css/main.css
KaiyuanRuanjianZhinanFix1/css/normalize.css
KaiyuanRuanjianZhinanFix1/css/popup.css
KaiyuanRuanjianZhinanFix1/font/__init__.py
KaiyuanRuanjianZhinanFix1/font/fontello.eot
KaiyuanRuanjianZhinanFix1/font/fontello.svg
KaiyuanRuanjianZhinanFix1/font/fontello.ttf
KaiyuanRuanjianZhinanFix1/font/fontello.woff
KaiyuanRuanjianZhinanFix1/img/__init__.py
KaiyuanRuanjianZhinanFix1/img/annotator-glyph-sprite.png
KaiyuanRuanjianZhinanFix1/img/annotator-icon-sprite.png
KaiyuanRuanjianZhinanFix1/img/apple-touch-icon.png
KaiyuanRuanjianZhinanFix1/img/cancelfullscreen.png
KaiyuanRuanjianZhinanFix1/img/close.png
KaiyuanRuanjianZhinanFix1/img/fullscreen.png
KaiyuanRuanjianZhinanFix1/img/loader.gif
KaiyuanRuanjianZhinanFix1/img/menu-icon.png
KaiyuanRuanjianZhinanFix1/img/save.png
KaiyuanRuanjianZhinanFix1/img/saved.png
KaiyuanRuanjianZhinanFix1/img/settings-s.png
KaiyuanRuanjianZhinanFix1/img/settings.png
KaiyuanRuanjianZhinanFix1/img/star.png
KaiyuanRuanjianZhinanFix1/js/__init__.py
KaiyuanRuanjianZhinanFix1/js/epub.js
KaiyuanRuanjianZhinanFix1/js/epub.min.js
KaiyuanRuanjianZhinanFix1/js/epub.min.map
KaiyuanRuanjianZhinanFix1/js/hooks.min.js
KaiyuanRuanjianZhinanFix1/js/hooks.min.map
KaiyuanRuanjianZhinanFix1/js/reader.js
KaiyuanRuanjianZhinanFix1/js/reader.js.map
KaiyuanRuanjianZhinanFix1/js/reader.min.js
KaiyuanRuanjianZhinanFix1/js/reader.min.map
KaiyuanRuanjianZhinanFix1/js/hooks/__init__.py
KaiyuanRuanjianZhinanFix1/js/hooks/extensions/__init__.py
KaiyuanRuanjianZhinanFix1/js/hooks/extensions/highlight.js
KaiyuanRuanjianZhinanFix1/js/libs/__init__.py
KaiyuanRuanjianZhinanFix1/js/libs/jquery.min.js
KaiyuanRuanjianZhinanFix1/js/libs/localforage.min.js
kaiyuan_ruanjian_zhinan_fix1-2025.3.24.0.dist-info/METADATA
kaiyuan_ruanjian_zhinan_fix1-2025.3.24.0.dist-info/WHEEL
kaiyuan_ruanjian_zhinan_fix1-2025.3.24.0.dist-info/entry_points.txt
kaiyuan_ruanjian_zhinan_fix1-2025.3.24.0.dist-info/top_level.txt
kaiyuan_ruanjian_zhinan_fix1-2025.3.24.0.dist-info/RECORD
